wlitellms/__init__.py
wlitellms/config/__init__.py
wlitellms/config/agents.py
wlitellms/config/env.py
wlitellms/config/loader.py
wlitellms/llms/__init__.py
wlitellms/llms/callbacks.py
wlitellms/llms/litellm_v2.py
wlitellms/llms/llm.py
wlitellms-0.1.4.dist-info/LICENSE
wlitellms-0.1.4.dist-info/METADATA
wlitellms-0.1.4.dist-info/WHEEL
wlitellms-0.1.4.dist-info/top_level.txt
wlitellms-0.1.4.dist-info/RECORD
